wkconnect/__init__.py
wkconnect/__main__.py
wkconnect/backends/__init__.py
wkconnect/backends/backend.py
wkconnect/backends/boss/__init__.py
wkconnect/backends/boss/backend.py
wkconnect/backends/boss/client.py
wkconnect/backends/boss/models.py
wkconnect/backends/boss/token_repository.py
wkconnect/backends/neuroglancer/__init__.py
wkconnect/backends/neuroglancer/backend.py
wkconnect/backends/neuroglancer/models.py
wkconnect/backends/tiff/__init__.py
wkconnect/backends/tiff/backend.py
wkconnect/backends/tiff/models.py
wkconnect/backends/wkw/__init__.py
wkconnect/backends/wkw/backend.py
wkconnect/backends/wkw/models.py
wkconnect/repository.py
wkconnect/routes/__init__.py
wkconnect/routes/datasets/__init__.py
wkconnect/routes/datasets/datasource_properties.py
wkconnect/routes/datasets/histogram.py
wkconnect/routes/datasets/read_data.py
wkconnect/routes/datasets/thumbnail.py
wkconnect/routes/datasets/upload.py
wkconnect/routes/trace.py
wkconnect/routes/triggers.py
wkconnect/utils/__init__.py
wkconnect/utils/caching.py
wkconnect/utils/colors.py
wkconnect/utils/exceptions.py
wkconnect/utils/json.py
wkconnect/utils/scheduler.py
wkconnect/utils/si.py
wkconnect/utils/types.py
wkconnect/version.py
wkconnect/webknossos/__init__.py
wkconnect/webknossos/access.py
wkconnect/webknossos/client.py
wkconnect/webknossos/models.py
wkconnect-21.4.0.dist-info/LICENSE
wkconnect-21.4.0.dist-info/WHEEL
wkconnect-21.4.0.dist-info/METADATA
wkconnect-21.4.0.dist-info/RECORD
